taxonomy/__init__.py
taxonomy/admin.py
taxonomy/apps.py
taxonomy/constants.py
taxonomy/emsi_client.py
taxonomy/enums.py
taxonomy/exceptions.py
taxonomy/forms.py
taxonomy/models.py
taxonomy/urls.py
taxonomy/views.py
taxonomy/providers/__init__.py
taxonomy/providers/course_metadata.py
taxonomy/providers/utils.py
taxonomy/validators/__init__.py
taxonomy/validators/course_metadata.py
taxonomy_service-1.0.0.dist-info/LICENSE
taxonomy_service-1.0.0.dist-info/METADATA
taxonomy_service-1.0.0.dist-info/WHEEL
taxonomy_service-1.0.0.dist-info/top_level.txt
taxonomy_service-1.0.0.dist-info/RECORD
