Metadata-Version: 2.1
Name: taxonomy-service
Version: 1.0.0
Summary: Taxonomy service
Home-page: https://github.com/edx/taxonomy-service
Author: edX
Author-email: oscm@edx.org
License: MIT
Platform: UNKNOWN
Requires-Dist: Django
Requires-Dist: djangorestframework
Requires-Dist: django-model-utils
Requires-Dist: django-solo
Requires-Dist: pytz
Requires-Dist: edx-rest-api-client
Requires-Dist: edx-django-utils
